lapa_file_store/__init__.py
lapa_file_store/configuration.py
lapa_file_store/main.py
lapa_file_store/data/config.ini
lapa_file_store/utils/Helper.py
lapa_file_store/utils/__init__.py
lapa_file_store-0.0.13.dist-info/METADATA
lapa_file_store-0.0.13.dist-info/WHEEL
lapa_file_store-0.0.13.dist-info/top_level.txt
lapa_file_store-0.0.13.dist-info/RECORD
