Metadata-Version: 2.1
Name: lapa-file-store
Version: 0.0.13
Summary: file storage layer for my personal server.
Home-page: https://github.com/adityashetty35/lapa_file_store
Author: Aaditya sangishetty, thePmSquare, Amish Palkar
Author-email: adityashetty35@gmail.com, thepmsquare@gmail.com, amishpalkar302001@gmail.com
License: UNKNOWN
Platform: UNKNOWN
Classifier: Development Status :: 3 - Alpha
Classifier: Intended Audience :: Developers
Classifier: License :: OSI Approved :: MIT License
Classifier: Programming Language :: Python :: 3
Classifier: Programming Language :: Python :: 3.9
Requires-Dist: uvicorn >=0.24.0.post1
Requires-Dist: fastapi >=0.104.1
Requires-Dist: python-multipart >=0.0.6
Requires-Dist: pydantic >=2.5.3
Requires-Dist: pytest >=8.0.0
Requires-Dist: square-logger >=1.0.0
Requires-Dist: lapa-database-helper >=0.0.3
Requires-Dist: lapa-commons >=0.0.3
Requires-Dist: lapa-database-structure >=0.0.6
